[
    {
        "business_name": "Beth Protea Retirement Village",
        "address": "5 Asher Barash Street, Herzliya, Tel Aviv District, Israel",
        "telephone": "+972 9 959 5200 ",
        "email": "lynn@bethprotea.org.il",
        "website": "http://www.bethprotea.org.il"
    },
    {
        "business_name": "Wow Brows Tel Aviv",
        "address": "Tel Aviv-Yafo, Tel Aviv District, Israel",
        "telephone": null,
        "email": "anglolist@gmail.com",
        "website": null
    },
    {
        "business_name": "Families in Transition",
        "address": "Haifa, We work in the Haifa area, Israel",
        "telephone": null,
        "email": "anglolist@gmail.com",
        "website": null
    },
    {
        "business_name": "Deborah Bach Cognitive Behavioral Therapy in Haifa",
        "address": "Haifa, Israel",
        "telephone": "+ 972 54 652 3556",
        "email": "bachdeborah@hotmail.com",
        "website": null
    },
    {
        "business_name": "Jackie Galgut: Raanana Counselor & Family Therapist",
        "address": "Ra'anana, Raanana Kfar Saba, Israel",
        "telephone": "+972 9 745 4090",
        "email": "jackiegalgut@yahoo.com",
        "website": null
    },
    {
        "business_name": "Revital Kornfeld",
        "address": "Haifa, Israel",
        "telephone": null,
        "email": "",
        "website": null
    },
    {
        "business_name": "Robin Zeiger Clinical Psychologist",
        "address": "Netanya, Central District, Israel",
        "telephone": null,
        "email": "anglolist@gmail.com",
        "website": null
    },
    {
        "business_name": "Ellen Levinson: Haifa Psychotherapist & Social Worker",
        "address": "Rechov Moriah, Haifa, Northen Region, Israel",
        "telephone": "+972 54 679 4450 ",
        "email": "levinson.ellen@gmail.com",
        "website": null
    },
    {
        "business_name": "Holistic Psychotherapy & Workshops",
        "address": "Jerusalem, Jerusalem District, Israel",
        "telephone": null,
        "email": "anglolist@gmail.com",
        "website": null
    },
    {
        "business_name": "Dr Annette Berger",
        "address": "Jerusalem, Jerusalem District, Israel",
        "telephone": null,
        "email": "anglolist@gmail.com",
        "website": null
    },
    {
        "business_name": "English-speaking Cognitive-Behavioural Therapy",
        "address": "Jerusalem, Jerusalem District, Israel",
        "telephone": null,
        "email": "anglolist@gmail.com",
        "website": null
    },
    {
        "business_name": "Gavriel Tornek Meditation Workshops, Self-Help and Health",
        "address": "Rehovot, Central District, Israel",
        "telephone": null,
        "email": "",
        "website": null
    },
    {
        "business_name": "William Livingston",
        "address": "6 Yehuda HaNassi, Kiryat Tiv'on, Northen Region, Israel",
        "telephone": null,
        "email": "anglolist@gmail.com",
        "website": null
    },
    {
        "business_name": "Acupuncture & Oriental Medicine",
        "address": "Haifa, Haifa & Hadera, Israel",
        "telephone": null,
        "email": "anglolist@gmail.com",
        "website": null
    },
    {
        "business_name": "Shai's Yin & Yang",
        "address": "Haifa, Northen Region, Israel",
        "telephone": null,
        "email": "anglolist@gmail.com",
        "website": null
    },
    {
        "business_name": "Dr Jacob Gordon DDS",
        "address": "2/4 Ha Elanot St., Karmiel, Northern Israel, Israel",
        "telephone": null,
        "email": "anglolist@gmail.com",
        "website": null
    },
    {
        "business_name": "Dr Avraham & Dr Yitzhak Moshiachov",
        "address": "9 Rechov Ben Hillel 9, Jerusalem, Jerusalem, Jerusalem and environs, Israel",
        "telephone": "#",
        "email": "anglolist@gmail.com",
        "website": null
    },
    {
        "business_name": "Dr Alan Permut D D S",
        "address": "# #, Haifa, Northern Israel, Israel",
        "telephone": null,
        "email": "",
        "website": null
    },
    {
        "business_name": "Dr Jacob Hans - Chiropractor",
        "address": "38 Hanassi, Haifa, Northern Israel, Israel",
        "telephone": null,
        "email": "anglolist@gmail.com",
        "website": null
    },
    {
        "business_name": "Society for the Prevention of Blindness",
        "address": "32 HaGefen, Haifa, Head Office: Haifa, Israel",
        "telephone": "04 852 7222",
        "email": "anglolist@gmail.com",
        "website": "http://www.blindhaifa.org.il"
    }
]